mcp_server.py
train.py
authring-0.0.1.dist-info/LICENSE
authring-0.0.1.dist-info/METADATA
authring-0.0.1.dist-info/WHEEL
authring-0.0.1.dist-info/top_level.txt
authring-0.0.1.dist-info/RECORD
