Metadata-Version: 2.2
Name: authring
Version: 0.0.1
Summary: Authring is an MCP-driven guardrails system that evaluates code modification proposals based on historical impact, contributor expertise, and production risk assessment. The system utilizes: Astra DB for historical data storage, Unstructured.io for document parsing, Langflow for AI-driven decision-making, Twilio for real-time human validation, and GitHub CLI (gh) for managing patch review links.
Author-email: Chris McKenzie <hello@noblox.pro>
License: MIT License
Project-URL: Bug Tracker, https://github.com/nblx-org/authring
Project-URL: Homepage, https://authring.org
Project-URL: Repository, https://github.com/nblx-org/authring
Classifier: Development Status :: 3 - Alpha
Classifier: Intended Audience :: Developers
Classifier: Topic :: Software Development :: Build Tools
Classifier: License :: OSI Approved :: MIT License
Classifier: Programming Language :: Python :: 3
Classifier: Programming Language :: Python :: 3.7
Classifier: Programming Language :: Python :: 3.8
Classifier: Programming Language :: Python :: 3.9
Classifier: Programming Language :: Python :: 3.10
Classifier: Programming Language :: Python :: 3 :: Only
License-File: LICENSE
Requires-Dist: astra-db
Requires-Dist: cassandra-driver
Requires-Dist: cassio
Requires-Dist: fastmcp
Requires-Dist: gitpython
Requires-Dist: radon
Requires-Dist: tree-sitter
Requires-Dist: unstructured
